{
	"type": "FeatureCollection",
	"features": [
		{
			"id": "1",
			"type": "Feature",
			"properties": {
				"marker-color": "#7e7e7e",
				"marker-size": "medium",
				"marker-symbol": "Verkeersregelaar",
				"zoom-level": 14,
				"title": "Verkeersregelaar",
				"description": "Verkeersregelaar Haaswijklaan."
			},
			"geometry": {
				"coordinates": [
					 4.474230408668517,
                                         52.196552072225806
				],
				"type": "Point"
			}
		},
		{
			"id": "2",
			"type": "Feature",
			"properties": {
				"marker-color": "#7e7e7e",
				"marker-size": "medium",
				"marker-symbol": "Verkeersregelaar",
				"zoom-level": 14,
				"title": "Verkeersregelaar",
				"description": "Verkeersregelaar Haarlemmerstraatweg 1"
			},
			"geometry": {
				"coordinates": [
					     4.469638466835022,
                                             52.1952544691756
				],
				"type": "Point"
			}
		},
		{
			"id": "3",
			"type": "Feature",
			"properties": {
				"marker-color": "#7e7e7e",
				"marker-size": "medium",
				"marker-symbol": "Verkeersregelaar",
				"zoom-level": 14,
				"title": "Verkeersregelaar",
				"description": "Verkeersregelaar Haarlemmerstraatweg 2"
			},
			"geometry": {
				"coordinates": [
					4.467771649360657,
          				52.192916468546606
				],
				"type": "Point"
			}
		},
		{
			"id": "4",
			"type": "Feature",
			"properties": {
				"marker-color": "#7e7e7e",
				"marker-size": "medium",
				"marker-symbol": "Verkeersregelaar",
				"zoom-level": 14,
				"title": "Verkeersregelaar",
				"description": "Verkeersregelaar Kerckwervelaan 1"
			},
			"geometry": {
				"coordinates": [
				          4.4738709926605225,
				          52.193123638124526
				],
				"type": "Point"
			}
		},
				{
			"id": "5",
			"type": "Feature",
			"properties": {
				"marker-color": "#7e7e7e",
				"marker-size": "medium",
				"marker-symbol": "Verkeersregelaar",
				"zoom-level": 14,
				"title": "Verkeersregelaar",
				"description": "Verkeersregelaar Kerckwervelaan 2"
			},
			"geometry": {
				"coordinates": [
					4.467771649360657,
          				52.192916468546606
				],
				"type": "Point"
			}
		},
		{
			"id": "6",
			"type": "Feature",
			"properties": {
				"marker-color": "#7e7e7e",
				"marker-size": "medium",
				"marker-symbol": "Start",
				"zoom-level": 14,
				"title": "Start",
				"description": "Vandaag een Rondje Haaswijk"
			},
			"geometry": {
				"coordinates": [
  			        4.4745951890945435,
   			       52.19141034957684
				],
				"type": "Point"
			}
		},
		{
			"id": "7",
			"type": "Feature",
			"properties": {
				"marker-color": "#7e7e7e",
				"marker-size": "medium",
				"marker-symbol": "Finish",
				"zoom-level": 14,
				"title": "Finish",
				"description": "Vergeet niet je medaile op te halen"
			},
			"geometry": {
				"coordinates": [
          				4.4747453927993766,
          				52.19164712275148
				],
				"type": "Point"
			}
		}
	]
}
