{
	"type": "FeatureCollection",
	"features": [
		{
			"id": "1",
			"type": "Feature",
			"properties": {
				"marker-color": "#7e7e7e",
				"marker-size": "medium",
				"marker-symbol": "Verkeersregelaar",
				"zoom-level": 14,
				"title": "Verkeersregelaar",
				"description": "Verkeersregelaar Haaswijklaan."
			},
			"geometry": {
				"coordinates": [
					 4.474230408668517,
                                         52.196552072225806
				],
				"type": "Point"
			}
		},
		{
			"id": "2",
			"type": "Feature",
			"properties": {
				"marker-color": "#7e7e7e",
				"marker-size": "medium",
				"marker-symbol": "Verkeersregelaar",
				"zoom-level": 14,
				"title": "Verkeersregelaar",
				"description": "Verkeersregelaar Haarlemmerstraatweg 1"
			},
			"geometry": {
				"coordinates": [
					     4.469638466835022,
                                             52.1952544691756
				],
				"type": "Point"
			}
		},
		{
			"id": "3",
			"type": "Feature",
			"properties": {
				"marker-color": "#7e7e7e",
				"marker-size": "medium",
				"marker-symbol": "Verkeersregelaar",
				"zoom-level": 14,
				"title": "Verkeersregelaar",
				"description": "Verkeersregelaar Haarlemmerstraatweg 2"
			},
			"geometry": {
				"coordinates": [
					4.467771649360657,
          				52.192916468546606
				],
				"type": "Point"
			}
		}
		{
			"id": "4",
			"type": "Feature",
			"properties": {
				"marker-color": "#7e7e7e",
				"marker-size": "medium",
				"marker-symbol": "Verkeersregelaar",
				"zoom-level": 14,
				"title": "Verkeersregelaar",
				"description": "Verkeersregelaar Haaswijklaan"
			},
			"geometry": {
				"coordinates": [
          				4.4751691818237305,
          				52.19278328759382
				],
				"type": "Point"
			}
		}
		{
			"id": "4",
			"type": "Feature",
			"properties": {
				"marker-color": "#7e7e7e",
				"marker-size": "medium",
				"marker-symbol": "Verkeersregelaar",
				"zoom-level": 14,
				"title": "Verkeersregelaar",
				"description": "Verkeersregelaar Kleyn Profijtlaan"
			},
			"geometry": {
				"coordinates": [
          				4.475163817405701,
          				52.192492261160325
				],
				"type": "Point"
			}
		}
	]
}
