{
	"type": "FeatureCollection",
	"features": [
		{
			"id": "1",
			"type": "Feature",
			"properties": {
				"marker-color": "#7e7e7e",
				"marker-size": "medium",
				"marker-symbol": "Start",
				"zoom-level": 14,
				"title": "Start",
				"description": ""
			},
			"geometry": {
				"coordinates": [
       	          	          4.474646151065826,
			          52.19135608888004
				],
				"type": "Point"
			}
		},
			{
			"id": "2",
			"type": "Feature",
			"properties": {
				"marker-color": "#7e7e7e",
				"marker-size": "medium",
				"marker-symbol": "Finish",
				"zoom-level": 14,
				"title": "Finish",
				"description": ""
			},
			"geometry": {
				"coordinates": [
          		           4.475222826004028,
     				     52.1915599772158
				],
				"type": "Point"
			}
		}
	]
}
